settings/__init__.py
sqlsettingslib/__init__.py
sqlsettingslib-0.0.4.dist-info/LICENSE
sqlsettingslib-0.0.4.dist-info/METADATA
sqlsettingslib-0.0.4.dist-info/WHEEL
sqlsettingslib-0.0.4.dist-info/top_level.txt
sqlsettingslib-0.0.4.dist-info/RECORD
