Metadata-Version: 2.1
Name: sqlsettingslib
Version: 0.0.4
Summary: Store settings in a sql database
Home-page: https://gitlab.com/Raspilot/sqlsettingslib
Author: Fabian Becker
Author-email: fab.becker@outlook.de
License: UNKNOWN
Platform: UNKNOWN
Classifier: Programming Language :: Python :: 3
Classifier: License :: OSI Approved :: GNU General Public License v3 (GPLv3)
Classifier: Operating System :: OS Independent
Requires-Python: >=3.6
